toolkit_python/__init__.py
toolkit_python/generics/__init__.py
toolkit_python/generics/app_generic_model.py
toolkit_python/generics/app_generic_service.py
toolkit_python/utils/__init__.py
toolkit_python/utils/app_db_utils.py
toolkit_python/utils/app_decorator_utils.py
toolkit_python/utils/app_errorhandler_utils.py
toolkit_python/utils/app_exception_utils.py
toolkit_python/utils/app_resource_utils.py
toolkit_python/utils/app_schema_field_utils.py
toolkit_python/utils/app_validator_utils.py
toolkit_python-1.0.7.dist-info/METADATA
toolkit_python-1.0.7.dist-info/WHEEL
toolkit_python-1.0.7.dist-info/top_level.txt
toolkit_python-1.0.7.dist-info/RECORD
