Metadata-Version: 2.1
Name: toolkit-python
Version: 1.0.7
Summary: Toolkit Python
Home-page: UNKNOWN
Author: Eduardo Junqueira
License: MIT
Platform: UNKNOWN
Requires-Python: >=3.6
